{
    "id": "Garen",
    "key": "86",
    "name": "Garen",
    "tags": [
        "Fighter",
        "Tank"
    ],
    "partype": "None",
    "info": {
        "attack": 7,
        "defense": 7,
        "magic": 1,
        "difficulty": 5
    },
    "stats": {
        "hp": 690,
        "hpperlevel": 98,
        "mp": 0,
        "mpperlevel": 0,
        "movespeed": 340,
        "armor": 38,
        "armorperlevel": 4.2,
        "spellblock": 32,
        "spellblockperlevel": 1.55,
        "attackrange": 175,
        "hpregen": 8,
        "hpregenperlevel": 0.5,
        "mpregen": 0,
        "mpregenperlevel": 0,
        "crit": 0,
        "critperlevel": 0,
        "attackdamage": 69,
        "attackdamageperlevel": 4.5,
        "attackspeedperlevel": 3.65,
        "attackspeed": 0.625
    },
    "gamestats": {
        "IRON": {
            "gamesrecorded": 3051,
            "frequency_TOP": 2599,
            "frequency_JUNGLE": 193,
            "frequency_MIDDLE": 174,
            "frequency_BOTTOM": 40,
            "frequency_UTILITY": 45,
            "total_wins_TOP": 1327,
            "total_wins_JUNGLE": 95,
            "total_wins_MIDDLE": 93,
            "total_wins_BOTTOM": 21,
            "total_wins_UTILITY": 25,
            "total_assists": 12135,
            "total_detectorWardsPlaced": 874,
            "total_dragonKills": 427,
            "total_goldEarned": 34559335,
            "total_kills": 19045,
            "total_deaths": 15032,
            "total_magicDamageDealtToChampions": 624970,
            "total_physicalDamageDealtToChampions": 43640779,
            "total_physicalDamageTaken": 55242395,
            "total_magicDamageTaken": 31663248,
            "total_timeCCingOthers": 93764,
            "total_totalDamageDealtToChampions": 57771537,
            "total_totalDamageShieldedOnTeammates": 3197,
            "total_totalDamageTaken": 92156575,
            "total_totalHeal": 9630861,
            "total_visionScore": 41869,
            "total_win": 1561,
            "total_damagePerMinute": 83917.93452469683,
            "total_effectiveHealAndShielding": 364.1600036621094,
            "average_frequency_TOP": 0.8518518518518519,
            "average_frequency_JUNGLE": 0.06325794821370043,
            "average_frequency_MIDDLE": 0.05703048180924287,
            "average_frequency_BOTTOM": 0.013110455588331694,
            "average_frequency_UTILITY": 0.014749262536873156,
            "average_wins_TOP": 0.510580992689496,
            "average_wins_JUNGLE": 0.49222797927461137,
            "average_wins_MIDDLE": 0.5344827586206896,
            "average_wins_BOTTOM": 0.525,
            "average_wins_UTILITY": 0.5555555555555556,
            "average_assists": 3.977384464110128,
            "average_detectorWardsPlaced": 0.2864634546050475,
            "average_dragonKills": 0.13995411340544084,
            "average_goldEarned": 11327.215666994429,
            "average_kills": 6.242215666994428,
            "average_deaths": 4.926909210095051,
            "average_magicDamageDealtToChampions": 204.84103572599147,
            "average_physicalDamageDealtToChampions": 14303.762372992462,
            "average_physicalDamageTaken": 18106.32415601442,
            "average_magicDamageTaken": 10377.990167158308,
            "average_timeCCingOthers": 30.732218944608324,
            "average_totalDamageDealtToChampions": 18935.279252704033,
            "average_totalDamageShieldedOnTeammates": 1.0478531628974106,
            "average_totalDamageTaken": 30205.367092756474,
            "average_totalHeal": 3156.624385447394,
            "average_visionScore": 13.723041625696492,
            "average_win": 0.5116355293346444,
            "average_damagePerMinute": 27.50505884126412,
            "average_effectiveHealAndShielding": 0.1193575888764698
        },
        "BRONZE": {
            "gamesrecorded": 2648,
            "frequency_TOP": 2221,
            "frequency_JUNGLE": 145,
            "frequency_MIDDLE": 172,
            "frequency_BOTTOM": 58,
            "frequency_UTILITY": 52,
            "total_wins_TOP": 1192,
            "total_wins_JUNGLE": 76,
            "total_wins_MIDDLE": 81,
            "total_wins_BOTTOM": 29,
            "total_wins_UTILITY": 25,
            "total_assists": 11416,
            "total_detectorWardsPlaced": 1023,
            "total_dragonKills": 361,
            "total_goldEarned": 31806791,
            "total_kills": 16917,
            "total_deaths": 13333,
            "total_magicDamageDealtToChampions": 658613,
            "total_physicalDamageDealtToChampions": 40579914,
            "total_physicalDamageTaken": 50204663,
            "total_magicDamageTaken": 28550933,
            "total_timeCCingOthers": 88594,
            "total_totalDamageDealtToChampions": 53698692,
            "total_totalDamageShieldedOnTeammates": 1222,
            "total_totalDamageTaken": 83686257,
            "total_totalHeal": 8659526,
            "total_visionScore": 41488,
            "total_win": 1403,
            "total_damagePerMinute": 70181.9561966144,
            "total_effectiveHealAndShielding": 0,
            "average_frequency_TOP": 0.8387462235649547,
            "average_frequency_JUNGLE": 0.0547583081570997,
            "average_frequency_MIDDLE": 0.0649546827794562,
            "average_frequency_BOTTOM": 0.02190332326283988,
            "average_frequency_UTILITY": 0.019637462235649546,
            "average_wins_TOP": 0.5366951823502927,
            "average_wins_JUNGLE": 0.5241379310344828,
            "average_wins_MIDDLE": 0.47093023255813954,
            "average_wins_BOTTOM": 0.5,
            "average_wins_UTILITY": 0.4807692307692308,
            "average_assists": 4.311178247734139,
            "average_detectorWardsPlaced": 0.38632930513595165,
            "average_dragonKills": 0.13632930513595165,
            "average_goldEarned": 12011.628021148037,
            "average_kills": 6.388595166163142,
            "average_deaths": 5.03512084592145,
            "average_magicDamageDealtToChampions": 248.72092145015105,
            "average_physicalDamageDealtToChampions": 15324.74093655589,
            "average_physicalDamageTaken": 18959.46487915408,
            "average_magicDamageTaken": 10782.074395770393,
            "average_timeCCingOthers": 33.45694864048338,
            "average_totalDamageDealtToChampions": 20278.962235649546,
            "average_totalDamageShieldedOnTeammates": 0.46148036253776437,
            "average_totalDamageTaken": 31603.571374622356,
            "average_totalHeal": 3270.213746223565,
            "average_visionScore": 15.667673716012084,
            "average_win": 0.529833836858006,
            "average_damagePerMinute": 26.503759892981268,
            "average_effectiveHealAndShielding": 0.0
        },
        "SILVER": {
            "gamesrecorded": 2779,
            "frequency_TOP": 2325,
            "frequency_JUNGLE": 155,
            "frequency_MIDDLE": 205,
            "frequency_BOTTOM": 50,
            "frequency_UTILITY": 44,
            "total_wins_TOP": 1218,
            "total_wins_JUNGLE": 67,
            "total_wins_MIDDLE": 118,
            "total_wins_BOTTOM": 27,
            "total_wins_UTILITY": 26,
            "total_assists": 12016,
            "total_detectorWardsPlaced": 1182,
            "total_dragonKills": 391,
            "total_goldEarned": 34463899,
            "total_kills": 17973,
            "total_deaths": 14344,
            "total_magicDamageDealtToChampions": 565191,
            "total_physicalDamageDealtToChampions": 44035941,
            "total_physicalDamageTaken": 54270141,
            "total_magicDamageTaken": 29834005,
            "total_timeCCingOthers": 95065,
            "total_totalDamageDealtToChampions": 57998114,
            "total_totalDamageShieldedOnTeammates": 0,
            "total_totalDamageTaken": 89621881,
            "total_totalHeal": 9178143,
            "total_visionScore": 45796,
            "total_win": 1456,
            "total_damagePerMinute": 103386.39077825144,
            "total_effectiveHealAndShielding": 0,
            "average_frequency_TOP": 0.8366318819719324,
            "average_frequency_JUNGLE": 0.05577545879812882,
            "average_frequency_MIDDLE": 0.07376754228139619,
            "average_frequency_BOTTOM": 0.017992083483267363,
            "average_frequency_UTILITY": 0.01583303346527528,
            "average_wins_TOP": 0.5238709677419355,
            "average_wins_JUNGLE": 0.432258064516129,
            "average_wins_MIDDLE": 0.5756097560975609,
            "average_wins_BOTTOM": 0.54,
            "average_wins_UTILITY": 0.5909090909090909,
            "average_assists": 4.323857502698813,
            "average_detectorWardsPlaced": 0.42533285354444045,
            "average_dragonKills": 0.14069809283915077,
            "average_goldEarned": 12401.546959337891,
            "average_kills": 6.467434328895286,
            "average_deaths": 5.161568909679741,
            "average_magicDamageDealtToChampions": 203.37927311982727,
            "average_physicalDamageDealtToChampions": 15845.966534724721,
            "average_physicalDamageTaken": 19528.65815041382,
            "average_magicDamageTaken": 10735.518172004318,
            "average_timeCCingOthers": 34.208348326736235,
            "average_totalDamageDealtToChampions": 20870.138179201153,
            "average_totalDamageShieldedOnTeammates": 0.0,
            "average_totalDamageTaken": 32249.687297589062,
            "average_totalHeal": 3302.6783015473193,
            "average_visionScore": 16.479309103994243,
            "average_win": 0.5239294710327456,
            "average_damagePerMinute": 37.20273147832006,
            "average_effectiveHealAndShielding": 0.0
        },
        "GOLD": {
            "gamesrecorded": 2460,
            "frequency_TOP": 2063,
            "frequency_JUNGLE": 144,
            "frequency_MIDDLE": 186,
            "frequency_BOTTOM": 32,
            "frequency_UTILITY": 35,
            "total_wins_TOP": 1068,
            "total_wins_JUNGLE": 79,
            "total_wins_MIDDLE": 114,
            "total_wins_BOTTOM": 26,
            "total_wins_UTILITY": 25,
            "total_assists": 10354,
            "total_detectorWardsPlaced": 1122,
            "total_dragonKills": 364,
            "total_goldEarned": 30429726,
            "total_kills": 15545,
            "total_deaths": 12226,
            "total_magicDamageDealtToChampions": 488275,
            "total_physicalDamageDealtToChampions": 38506167,
            "total_physicalDamageTaken": 47711392,
            "total_magicDamageTaken": 25220590,
            "total_timeCCingOthers": 84034,
            "total_totalDamageDealtToChampions": 50673417,
            "total_totalDamageShieldedOnTeammates": 993,
            "total_totalDamageTaken": 77762491,
            "total_totalHeal": 8022218,
            "total_visionScore": 41404,
            "total_win": 1312,
            "total_damagePerMinute": 89721.20118916752,
            "total_effectiveHealAndShielding": 0,
            "average_frequency_TOP": 0.8386178861788618,
            "average_frequency_JUNGLE": 0.05853658536585366,
            "average_frequency_MIDDLE": 0.07560975609756097,
            "average_frequency_BOTTOM": 0.013008130081300813,
            "average_frequency_UTILITY": 0.014227642276422764,
            "average_wins_TOP": 0.5176926805622879,
            "average_wins_JUNGLE": 0.5486111111111112,
            "average_wins_MIDDLE": 0.6129032258064516,
            "average_wins_BOTTOM": 0.8125,
            "average_wins_UTILITY": 0.7142857142857143,
            "average_assists": 4.208943089430894,
            "average_detectorWardsPlaced": 0.4560975609756098,
            "average_dragonKills": 0.14796747967479676,
            "average_goldEarned": 12369.807317073171,
            "average_kills": 6.319105691056911,
            "average_deaths": 4.969918699186992,
            "average_magicDamageDealtToChampions": 198.4857723577236,
            "average_physicalDamageDealtToChampions": 15652.913414634146,
            "average_physicalDamageTaken": 19394.87479674797,
            "average_magicDamageTaken": 10252.272357723577,
            "average_timeCCingOthers": 34.16016260162602,
            "average_totalDamageDealtToChampions": 20598.95,
            "average_totalDamageShieldedOnTeammates": 0.4036585365853659,
            "average_totalDamageTaken": 31610.768699186992,
            "average_totalHeal": 3261.0642276422764,
            "average_visionScore": 16.83089430894309,
            "average_win": 0.5333333333333333,
            "average_damagePerMinute": 36.47203300372664,
            "average_effectiveHealAndShielding": 0.0
        },
        "PLATINUM": {
            "gamesrecorded": 2319,
            "frequency_TOP": 1966,
            "frequency_JUNGLE": 106,
            "frequency_MIDDLE": 179,
            "frequency_BOTTOM": 34,
            "frequency_UTILITY": 34,
            "total_wins_TOP": 1000,
            "total_wins_JUNGLE": 51,
            "total_wins_MIDDLE": 96,
            "total_wins_BOTTOM": 20,
            "total_wins_UTILITY": 18,
            "total_assists": 9474,
            "total_detectorWardsPlaced": 1124,
            "total_dragonKills": 253,
            "total_goldEarned": 28874164,
            "total_kills": 14077,
            "total_deaths": 11827,
            "total_magicDamageDealtToChampions": 415817,
            "total_physicalDamageDealtToChampions": 36013447,
            "total_physicalDamageTaken": 44605240,
            "total_magicDamageTaken": 24461354,
            "total_timeCCingOthers": 78562,
            "total_totalDamageDealtToChampions": 47261072,
            "total_totalDamageShieldedOnTeammates": 0,
            "total_totalDamageTaken": 73615586,
            "total_totalHeal": 6990043,
            "total_visionScore": 39516,
            "total_win": 1185,
            "total_damagePerMinute": 80216.73847056627,
            "total_effectiveHealAndShielding": 0,
            "average_frequency_TOP": 0.8477792151789565,
            "average_frequency_JUNGLE": 0.04570935748167314,
            "average_frequency_MIDDLE": 0.0771884432945235,
            "average_frequency_BOTTOM": 0.014661492022423459,
            "average_frequency_UTILITY": 0.014661492022423459,
            "average_wins_TOP": 0.508646998982706,
            "average_wins_JUNGLE": 0.4811320754716981,
            "average_wins_MIDDLE": 0.5363128491620112,
            "average_wins_BOTTOM": 0.5882352941176471,
            "average_wins_UTILITY": 0.5294117647058824,
            "average_assists": 4.085381630012937,
            "average_detectorWardsPlaced": 0.4846916774471755,
            "average_dragonKills": 0.10909874946097456,
            "average_goldEarned": 12451.127210004312,
            "average_kills": 6.070288917636913,
            "average_deaths": 5.10004312203536,
            "average_magicDamageDealtToChampions": 179.3087537731781,
            "average_physicalDamageDealtToChampions": 15529.731349719706,
            "average_physicalDamageTaken": 19234.68736524364,
            "average_magicDamageTaken": 10548.233721431652,
            "average_timeCCingOthers": 33.877533419577404,
            "average_totalDamageDealtToChampions": 20379.936179387667,
            "average_totalDamageShieldedOnTeammates": 0.0,
            "average_totalDamageTaken": 31744.539025442,
            "average_totalHeal": 3014.2488141440276,
            "average_visionScore": 17.040103492884864,
            "average_win": 0.5109961190168176,
            "average_damagePerMinute": 34.591090327971656,
            "average_effectiveHealAndShielding": 0.0
        },
        "EMERALD": {
            "gamesrecorded": 2060,
            "frequency_TOP": 1735,
            "frequency_JUNGLE": 84,
            "frequency_MIDDLE": 182,
            "frequency_BOTTOM": 28,
            "frequency_UTILITY": 31,
            "total_wins_TOP": 903,
            "total_wins_JUNGLE": 43,
            "total_wins_MIDDLE": 95,
            "total_wins_BOTTOM": 15,
            "total_wins_UTILITY": 16,
            "total_assists": 8329,
            "total_detectorWardsPlaced": 1008,
            "total_dragonKills": 203,
            "total_goldEarned": 25728848,
            "total_kills": 12518,
            "total_deaths": 10149,
            "total_magicDamageDealtToChampions": 406705,
            "total_physicalDamageDealtToChampions": 31884502,
            "total_physicalDamageTaken": 39109387,
            "total_magicDamageTaken": 21129877,
            "total_timeCCingOthers": 70351,
            "total_totalDamageDealtToChampions": 41763012,
            "total_totalDamageShieldedOnTeammates": 0,
            "total_totalDamageTaken": 64149053,
            "total_totalHeal": 5901709,
            "total_visionScore": 34423,
            "total_win": 1072,
            "total_damagePerMinute": 83807.55545391775,
            "total_effectiveHealAndShielding": 0,
            "average_frequency_TOP": 0.8422330097087378,
            "average_frequency_JUNGLE": 0.040776699029126215,
            "average_frequency_MIDDLE": 0.0883495145631068,
            "average_frequency_BOTTOM": 0.013592233009708738,
            "average_frequency_UTILITY": 0.015048543689320388,
            "average_wins_TOP": 0.5204610951008646,
            "average_wins_JUNGLE": 0.5119047619047619,
            "average_wins_MIDDLE": 0.521978021978022,
            "average_wins_BOTTOM": 0.5357142857142857,
            "average_wins_UTILITY": 0.5161290322580645,
            "average_assists": 4.043203883495146,
            "average_detectorWardsPlaced": 0.4893203883495146,
            "average_dragonKills": 0.09854368932038834,
            "average_goldEarned": 12489.73203883495,
            "average_kills": 6.076699029126214,
            "average_deaths": 4.926699029126214,
            "average_magicDamageDealtToChampions": 197.42961165048544,
            "average_physicalDamageDealtToChampions": 15477.91359223301,
            "average_physicalDamageTaken": 18985.13932038835,
            "average_magicDamageTaken": 10257.221844660195,
            "average_timeCCingOthers": 34.150970873786406,
            "average_totalDamageDealtToChampions": 20273.306796116503,
            "average_totalDamageShieldedOnTeammates": 0.0,
            "average_totalDamageTaken": 31140.316990291263,
            "average_totalHeal": 2864.907281553398,
            "average_visionScore": 16.71019417475728,
            "average_win": 0.5203883495145631,
            "average_damagePerMinute": 40.68327934656202,
            "average_effectiveHealAndShielding": 0.0
        },
        "DIAMOND": {
            "gamesrecorded": 1815,
            "frequency_TOP": 1535,
            "frequency_JUNGLE": 51,
            "frequency_MIDDLE": 190,
            "frequency_BOTTOM": 20,
            "frequency_UTILITY": 19,
            "total_wins_TOP": 772,
            "total_wins_JUNGLE": 31,
            "total_wins_MIDDLE": 104,
            "total_wins_BOTTOM": 15,
            "total_wins_UTILITY": 13,
            "total_assists": 7309,
            "total_detectorWardsPlaced": 660,
            "total_dragonKills": 173,
            "total_goldEarned": 22369702,
            "total_kills": 10347,
            "total_deaths": 8776,
            "total_magicDamageDealtToChampions": 248892,
            "total_physicalDamageDealtToChampions": 27245429,
            "total_physicalDamageTaken": 34392901,
            "total_magicDamageTaken": 17468026,
            "total_timeCCingOthers": 59665,
            "total_totalDamageDealtToChampions": 35548549,
            "total_totalDamageShieldedOnTeammates": 0,
            "total_totalDamageTaken": 55354632,
            "total_totalHeal": 4761112,
            "total_visionScore": 30370,
            "total_win": 935,
            "total_damagePerMinute": 55981.22599545197,
            "total_effectiveHealAndShielding": 0,
            "average_frequency_TOP": 0.8457300275482094,
            "average_frequency_JUNGLE": 0.02809917355371901,
            "average_frequency_MIDDLE": 0.1046831955922865,
            "average_frequency_BOTTOM": 0.011019283746556474,
            "average_frequency_UTILITY": 0.01046831955922865,
            "average_wins_TOP": 0.5029315960912052,
            "average_wins_JUNGLE": 0.6078431372549019,
            "average_wins_MIDDLE": 0.5473684210526316,
            "average_wins_BOTTOM": 0.75,
            "average_wins_UTILITY": 0.6842105263157895,
            "average_assists": 4.026997245179063,
            "average_detectorWardsPlaced": 0.36363636363636365,
            "average_dragonKills": 0.09531680440771349,
            "average_goldEarned": 12324.904683195593,
            "average_kills": 5.700826446280992,
            "average_deaths": 4.83526170798898,
            "average_magicDamageDealtToChampions": 137.13057851239668,
            "average_physicalDamageDealtToChampions": 15011.25564738292,
            "average_physicalDamageTaken": 18949.256749311295,
            "average_magicDamageTaken": 9624.256749311295,
            "average_timeCCingOthers": 32.8732782369146,
            "average_totalDamageDealtToChampions": 19585.97741046832,
            "average_totalDamageShieldedOnTeammates": 0.0,
            "average_totalDamageTaken": 30498.419834710745,
            "average_totalHeal": 2623.2022038567493,
            "average_visionScore": 16.732782369146005,
            "average_win": 0.5151515151515151,
            "average_damagePerMinute": 30.84365068619943,
            "average_effectiveHealAndShielding": 0.0
        }
    }
}